umiread/__init__.py
umiread/umi_extract.py
umiread/umi_stats.py
umiread-1.9.1.dist-info/LICENSE.txt
umiread-1.9.1.dist-info/METADATA
umiread-1.9.1.dist-info/WHEEL
umiread-1.9.1.dist-info/top_level.txt
umiread-1.9.1.dist-info/RECORD
