Metadata-Version: 2.1
Name: umiread
Version: 1.9.1
Summary: Lightweight utility for 10x single cell assays
Home-page: https://github.com/matt-sd-watson/umiread
Author: Matthew Watson
Author-email: matt.sd.watson@gmail.com
License: UNKNOWN
Download-URL: https://github.com/matt-sd-watson/umiread/archive/1.9.1.tar.gz
Platform: UNKNOWN
Classifier: Programming Language :: Python :: 3
Classifier: License :: OSI Approved :: MIT License
Classifier: Operating System :: OS Independent
Requires-Dist: numpy
Requires-Dist: pandas
Requires-Dist: matplotlib
